dataeyes_mcp_server/__init__.py
dataeyes_mcp_server/__main__.py
dataeyes_mcp_server/dataeyes.py
dataeyes_mcp_server-1.0.7.dist-info/METADATA
dataeyes_mcp_server-1.0.7.dist-info/WHEEL
dataeyes_mcp_server-1.0.7.dist-info/entry_points.txt
dataeyes_mcp_server-1.0.7.dist-info/licenses/LICENSE
dataeyes_mcp_server-1.0.7.dist-info/RECORD
