Metadata-Version: 2.4
Name: dataeyes-mcp-server
Version: 1.0.7
Summary: This is a MCP server for Dataeyes
Author-email: xhl <xuhualun@aliyun.com>
License-File: LICENSE
Requires-Python: >=3.10
Requires-Dist: httpx>=0.28.1
Requires-Dist: mcp[cli]>=1.9.4
